mcp_server_aliyun_observability/__init__.py
mcp_server_aliyun_observability/__main__.py
mcp_server_aliyun_observability/api_error.py
mcp_server_aliyun_observability/cli.py
mcp_server_aliyun_observability/config.py
mcp_server_aliyun_observability/logger.py
mcp_server_aliyun_observability/server.py
mcp_server_aliyun_observability/settings.py
mcp_server_aliyun_observability/utils.py
mcp_server_aliyun_observability/core/__init__.py
mcp_server_aliyun_observability/core/models.py
mcp_server_aliyun_observability/core/utils.py
mcp_server_aliyun_observability/toolkits/__init__.py
mcp_server_aliyun_observability/toolkits/iaas/__init__.py
mcp_server_aliyun_observability/toolkits/iaas/toolkit.py
mcp_server_aliyun_observability/toolkits/paas/__init__.py
mcp_server_aliyun_observability/toolkits/paas/data_toolkit.py
mcp_server_aliyun_observability/toolkits/paas/dataset_toolkit.py
mcp_server_aliyun_observability/toolkits/paas/entity_toolkit.py
mcp_server_aliyun_observability/toolkits/paas/time_utils.py
mcp_server_aliyun_observability/toolkits/paas/toolkit.py
mcp_server_aliyun_observability/toolkits/shared/__init__.py
mcp_server_aliyun_observability/toolkits/shared/toolkit.py
mcp_server_aliyun_observability-1.0.6.dist-info/METADATA
mcp_server_aliyun_observability-1.0.6.dist-info/WHEEL
mcp_server_aliyun_observability-1.0.6.dist-info/entry_points.txt
mcp_server_aliyun_observability-1.0.6.dist-info/RECORD
