Metadata-Version: 2.4
Name: mcp-server-aliyun-observability
Version: 1.0.6
Summary: aliyun observability mcp server
Requires-Python: >=3.10
Requires-Dist: aiohttp>=3.8.0
Requires-Dist: alibabacloud-arms20190808>=8.0.0
Requires-Dist: alibabacloud-cms20240330==3.1.0
Requires-Dist: alibabacloud-credentials>=1.0.1
Requires-Dist: alibabacloud-sls20201230==5.7.0
Requires-Dist: alibabacloud-sts20150401==1.1.6
Requires-Dist: jinja2>=3.1.0
Requires-Dist: mcp>=1.12.0
Requires-Dist: numpy
Requires-Dist: pandas>=2.3.0
Requires-Dist: pydantic>=2.10.0
Requires-Dist: pyyaml>=6.0
Requires-Dist: requests>=2.28.0
Requires-Dist: rich>=13.0.0
Requires-Dist: tenacity>=8.0.0
Provides-Extra: admin
Provides-Extra: dev
Requires-Dist: pytest-asyncio>=0.21.0; extra == 'dev'
Requires-Dist: pytest-cov>=4.0.0; extra == 'dev'
Requires-Dist: pytest-mock>=3.10.0; extra == 'dev'
Requires-Dist: pytest>=7.0.0; extra == 'dev'
